remoteinfologger/__init__.py
remoteinfologger/remoteinfologger.py
remoteinfologger-1.0.3.dist-info/LICENSE.txt
remoteinfologger-1.0.3.dist-info/METADATA
remoteinfologger-1.0.3.dist-info/WHEEL
remoteinfologger-1.0.3.dist-info/top_level.txt
remoteinfologger-1.0.3.dist-info/RECORD
